pylines/__init__.py
pylines/io.py
pylines/logger.py
pylines/tflow.py
pylines/torch.py
pylines-0.0.4.dist-info/LICENSE
pylines-0.0.4.dist-info/METADATA
pylines-0.0.4.dist-info/WHEEL
pylines-0.0.4.dist-info/top_level.txt
pylines-0.0.4.dist-info/RECORD
