Metadata-Version: 2.1
Name: pylines
Version: 0.0.4
Summary: work with large jsonline files with ease
Home-page: http://github.com/trisongz/pylines
Author: Tri Songz
Author-email: ts@scontentengine.ai
License: UNKNOWN
Keywords: json,json lines,jsonlines
Platform: UNKNOWN
Classifier: Programming Language :: Python :: 3
Classifier: License :: OSI Approved :: MIT License
Classifier: Operating System :: OS Independent
Classifier: Development Status :: 3 - Alpha
Classifier: Intended Audience :: Developers
Requires-Python: >3.4
License-File: LICENSE
Requires-Dist: pysimdjson
Provides-Extra: all
Requires-Dist: tensorflow (>=2.1.0) ; extra == 'all'
Requires-Dist: torch (>=1.0) ; extra == 'all'
Requires-Dist: google-cloud-storage ; extra == 'all'
Requires-Dist: smart-open[all] ; extra == 'all'
Requires-Dist: transformers ; extra == 'all'
Provides-Extra: cloud
Requires-Dist: tensorflow (>=2.1.0) ; extra == 'cloud'
Requires-Dist: google-cloud-storage ; extra == 'cloud'
Requires-Dist: smart-open[all] ; extra == 'cloud'
Provides-Extra: nlp
Requires-Dist: transformers ; extra == 'nlp'
